neutrosopy/__init__.py
neutrosopy/neutrosophic.py
neutrosopy-0.0.7.dist-info/LICENSE
neutrosopy-0.0.7.dist-info/METADATA
neutrosopy-0.0.7.dist-info/WHEEL
neutrosopy-0.0.7.dist-info/top_level.txt
neutrosopy-0.0.7.dist-info/RECORD
