Metadata-Version: 2.1
Name: neutrosopy
Version: 0.0.7
Summary: Class and utility functions for working with algebraic neutrosophic numbers.
Author-email: Galen Seilis <galen.seilis@seilis.ca>
Project-URL: Homepage, https://github.com/galenseilis/neutrosopy
Project-URL: Bug Tracker, https://github.com/galenseilis/neutrosopy/issues
Classifier: Programming Language :: Python :: 3
Classifier: License :: OSI Approved :: MIT License
Classifier: Operating System :: OS Independent
Requires-Python: >=3.7
License-File: LICENSE
